EHS/__init__.py
EHS/aliases.py
EHS/art.py
EHS/calc.py
EHS/chklib_clrscr.py
EHS/chkupd_speedtest.py
EHS/constants.py
EHS/editors.py
EHS/logger.py
EHS/shell.py
EHS/theme_manager.py
EHS/tools.py
EHS/tutorial.py
EHS/weather.py
archive/v1.0.0.py
archive/v1.0.1.py
archive/v1.0.2.py
archive/v1.0.3.py
archive/v1.0.4.py
archive/v1.0.4a.py
archive/v1.0.5.py
archive/v1.0.6.py
archive/v1.0.7.py
archive/v1.0.8.py
event_horizon_shell-1.1.2.post1.dist-info/licenses/LICENSE
event_horizon_shell-1.1.2.post1.dist-info/METADATA
event_horizon_shell-1.1.2.post1.dist-info/WHEEL
event_horizon_shell-1.1.2.post1.dist-info/entry_points.txt
event_horizon_shell-1.1.2.post1.dist-info/top_level.txt
event_horizon_shell-1.1.2.post1.dist-info/RECORD
