Metadata-Version: 2.4
Name: event-horizon-shell
Version: 1.1.2.post1
Summary: Event Horizon Shell - advanced terminal shell with multiple utilities
Author-email: QUIK1001 <your-email@example.com>
License: MIT
Classifier: Programming Language :: Python :: 3
Classifier: License :: OSI Approved :: MIT License
Classifier: Operating System :: OS Independent
Requires-Python: >=3.6
License-File: LICENSE
Requires-Dist: psutil
Requires-Dist: requests
Requires-Dist: colorama
Requires-Dist: packaging
Requires-Dist: art
Requires-Dist: rich
Dynamic: license-file
